{
  "sections": {
    "banner": {
      "type": "collection-banner",
      "settings": {
        "full_width": true,
        "allow_transparent_header": false,
        "enable_parallax": false,
        "show_collection_title": true,
        "show_collection_description": false,
        "show_collection_image": true,
        "collection_title_size": "h0",
        "image_size": "auto",
        "mobile_text_position": "place-self-center text-center",
        "desktop_text_position": "sm:place-self-center-start sm:text-start",
        "featured_product": "",
        "featured_product_heading": "Featured product",
        "text_color": "#ffffff",
        "overlay_color": "#6c5b4b",
        "overlay_opacity": 30
      }
    },
    "9fdc1847-6780-49ab-a505-596ad2d6b919": {
      "type": "collections-shop",
      "blocks": {
        "6caadb53-1206-4f63-abb6-3234883cc927": {
          "type": "textbutton",
          "settings": {
            "collection": "all",
            "collection_title": "所有商品",
            "link": "shopify:\/\/collections\/all"
          }
        },
        "3fee2c47-bceb-41b5-8ba5-0cc00a4c2cad": {
          "type": "textbutton",
          "settings": {
            "collection": "沙發-沙發桌",
            "collection_title": "",
            "link": ""
          }
        },
        "208e7195-8186-4f79-b280-1d5dbb39ff1a": {
          "type": "textbutton",
          "settings": {
            "collection": "床架-床組",
            "collection_title": "",
            "link": ""
          }
        },
        "6af6869a-ded6-4e11-8e16-252669c38c7b": {
          "type": "textbutton",
          "settings": {
            "collection": "書架",
            "collection_title": "",
            "link": ""
          }
        },
        "7f4a5582-3131-4bb8-867a-b90b133d1291": {
          "type": "textbutton",
          "settings": {
            "collection": "床墊",
            "collection_title": "",
            "link": ""
          }
        },
        "bda63c30-75b9-4ad7-bf0a-01521058b320": {
          "type": "textbutton",
          "settings": {
            "collection": "儲物櫃-抽屜",
            "collection_title": "",
            "link": ""
          }
        },
        "ae88602f-67f5-4d26-9d90-b179b8bd928c": {
          "type": "textbutton",
          "settings": {
            "collection": "兒童沙發-椅子",
            "collection_title": "",
            "link": ""
          }
        },
        "4d9d94bd-0d4b-473a-b00c-f2875c81c1fc": {
          "type": "textbutton",
          "settings": {
            "collection": "書桌",
            "collection_title": "",
            "link": ""
          }
        },
        "099188c0-0345-41b8-b87c-7449f4b3c90b": {
          "type": "textbutton",
          "settings": {
            "collection": "椅子",
            "collection_title": "",
            "link": ""
          }
        },
        "6daa768c-cd9f-422e-91e3-7f48bc05337c": {
          "type": "imagebutton",
          "settings": {
            "collection": "沙發-沙發桌"
          }
        },
        "8e2f449d-3d4d-4b05-a2c0-72f0ea3901e4": {
          "type": "imagebutton",
          "settings": {
            "collection": "床架-床組"
          }
        },
        "6921b616-1de9-421d-8721-58c4f4ff690e": {
          "type": "imagebutton",
          "settings": {
            "collection": "書架"
          }
        },
        "24dda340-8bf3-4d82-9b83-0bfdc1c739c0": {
          "type": "imagebutton",
          "settings": {
            "collection": "床墊"
          }
        },
        "d2d508cd-9110-48a0-80f0-ea0e8d9980cf": {
          "type": "imagebutton",
          "settings": {
            "collection": "儲物櫃-抽屜"
          }
        },
        "45879456-c772-4474-b494-ce5a50cc6825": {
          "type": "imagebutton",
          "settings": {
            "collection": "兒童沙發-椅子"
          }
        },
        "e46a7109-5a83-4183-9835-68e299549093": {
          "type": "imagebutton",
          "settings": {
            "collection": "書桌"
          }
        },
        "0174685b-626c-4f33-b56e-8563a2958284": {
          "type": "imagebutton",
          "settings": {
            "collection": "椅子"
          }
        }
      },
      "block_order": [
        "6caadb53-1206-4f63-abb6-3234883cc927",
        "3fee2c47-bceb-41b5-8ba5-0cc00a4c2cad",
        "208e7195-8186-4f79-b280-1d5dbb39ff1a",
        "6af6869a-ded6-4e11-8e16-252669c38c7b",
        "7f4a5582-3131-4bb8-867a-b90b133d1291",
        "bda63c30-75b9-4ad7-bf0a-01521058b320",
        "ae88602f-67f5-4d26-9d90-b179b8bd928c",
        "4d9d94bd-0d4b-473a-b00c-f2875c81c1fc",
        "099188c0-0345-41b8-b87c-7449f4b3c90b",
        "6daa768c-cd9f-422e-91e3-7f48bc05337c",
        "8e2f449d-3d4d-4b05-a2c0-72f0ea3901e4",
        "6921b616-1de9-421d-8721-58c4f4ff690e",
        "24dda340-8bf3-4d82-9b83-0bfdc1c739c0",
        "d2d508cd-9110-48a0-80f0-ea0e8d9980cf",
        "45879456-c772-4474-b494-ce5a50cc6825",
        "e46a7109-5a83-4183-9835-68e299549093",
        "0174685b-626c-4f33-b56e-8563a2958284"
      ],
      "settings": {
        "padding_top": 0,
        "padding_bottom": 70,
        "mobile_padding_top": 0,
        "mobile_padding_bottom": 20
      }
    },
    "fe97db31-543b-4849-b2be-8b75ad89be2a": {
      "type": "collection-all-products-tabs",
      "blocks": {
        "6bc4e199-d26d-4fc0-b036-b08d0715ba05": {
          "type": "producttabs",
          "settings": {
            "tab_name": "LIVING ROOM",
            "image": "shopify:\/\/shop_images\/LIVING_ROOM.jpg",
            "collection": "product-list_living-room",
            "tab_content_heading": "懂生活也懂你的心",
            "tab_content": "打造屬於你的時尚空間，讓夢想的客廳成為生活的一部分​",
            "horizontal_position_product_one": 55,
            "vertical_position_product_one": 66,
            "horizontal_position_product_two": 18,
            "vertical_position_product_two": 64,
            "horizontal_position_product_three": 37,
            "vertical_position_product_three": 37,
            "horizontal_position_product_four": 12,
            "vertical_position_product_four": 66,
            "horizontal_position_product_five": 67,
            "vertical_position_product_five": 66
          }
        },
        "5922cd9d-40f2-4ff0-8fb2-2ab42f13fbb5": {
          "type": "producttabs",
          "settings": {
            "tab_name": "BED ROOM",
            "image": "shopify:\/\/shop_images\/BED_ROOM.jpg",
            "collection": "product-list_bed-room",
            "tab_content_heading": "安穩舒適共織全家人的夢",
            "tab_content": "明亮自然的設計營造溫馨的臥室，靈活地適應家庭生活週期​",
            "horizontal_position_product_one": 7,
            "vertical_position_product_one": 49,
            "horizontal_position_product_two": 56,
            "vertical_position_product_two": 65,
            "horizontal_position_product_three": 25,
            "vertical_position_product_three": 63,
            "horizontal_position_product_four": 87,
            "vertical_position_product_four": 68,
            "horizontal_position_product_five": 22,
            "vertical_position_product_five": 28
          }
        },
        "62faac42-8d39-4c02-8ded-5a07540cb303": {
          "type": "producttabs",
          "settings": {
            "tab_name": "KIDS ROOM",
            "image": "shopify:\/\/shop_images\/KIDS_ROOM.jpg",
            "collection": "product-list_kids-room",
            "tab_content_heading": "用彩多打造多姿的童年時光​",
            "tab_content": "從遊戲到入睡，為孩子提供相親相愛的相處空間​",
            "horizontal_position_product_one": 25,
            "vertical_position_product_one": 62,
            "horizontal_position_product_two": 69,
            "vertical_position_product_two": 52,
            "horizontal_position_product_three": 45,
            "vertical_position_product_three": 50,
            "horizontal_position_product_four": 85,
            "vertical_position_product_four": 55,
            "horizontal_position_product_five": 45,
            "vertical_position_product_five": 66
          }
        },
        "producttabs_QNjV8g": {
          "type": "producttabs",
          "settings": {
            "tab_name": "STUDY ROOM",
            "image": "shopify:\/\/shop_images\/ff.jpg",
            "collection": "main_kids-room",
            "tab_content_heading": "為萬變而生的學習方案",
            "tab_content": "適應孩子成長的節奏，讓靈活、自由成為學習的日常​",
            "horizontal_position_product_one": 40,
            "vertical_position_product_one": 53,
            "horizontal_position_product_two": 87,
            "vertical_position_product_two": 25,
            "horizontal_position_product_three": 46,
            "vertical_position_product_three": 25,
            "horizontal_position_product_four": 66,
            "vertical_position_product_four": 36,
            "horizontal_position_product_five": 67,
            "vertical_position_product_five": 66
          }
        }
      },
      "block_order": [
        "6bc4e199-d26d-4fc0-b036-b08d0715ba05",
        "5922cd9d-40f2-4ff0-8fb2-2ab42f13fbb5",
        "62faac42-8d39-4c02-8ded-5a07540cb303",
        "producttabs_QNjV8g"
      ],
      "settings": {
        "heading": "參觀每個空間",
        "padding_top": 70,
        "padding_bottom": 100,
        "mobile_padding_top": 60,
        "mobile_padding_bottom": 30
      }
    },
    "main": {
      "type": "main-collection",
      "settings": {
        "products_per_page": 5000,
        "products_per_row_mobile": "2",
        "products_per_row_desktop": 4,
        "filter_layout": "horizontal",
        "show_sort_by": true,
        "show_filters": true,
        "show_filter_group_name": false,
        "show_color_swatch": true,
        "show_empty_filter_values": false,
        "show_filter_values_count": false,
        "open_first_filter_group": false
      }
    },
    "bf576fbe-9cd2-4b50-a98e-488e9f2f41cf": {
      "type": "blog-posts",
      "blocks": {
        "template--15040117276742__bf576fbe-9cd2-4b50-a98e-488e9f2f41cf-blog-1": {
          "type": "blog",
          "settings": {
            "blog": "magazine",
            "posts_count": 2,
            "stack_items": true
          }
        }
      },
      "block_order": [
        "template--15040117276742__bf576fbe-9cd2-4b50-a98e-488e9f2f41cf-blog-1"
      ],
      "disabled": true,
      "settings": {
        "full_width": true,
        "show_excerpt": false,
        "show_date": false,
        "show_author": false,
        "show_comments_count": false,
        "show_category": true,
        "subheading": "",
        "title": "More to discover",
        "content": "",
        "link_url": "",
        "link_text": "",
        "background": "",
        "background_gradient": "",
        "text_color": "",
        "heading_color": "",
        "heading_gradient": ""
      }
    },
    "29cc8af8-f336-4fe8-98cc-84888081750f": {
      "type": "product-blog-post",
      "settings": {
        "heading": "More To Discover",
        "padding_top": 120,
        "padding_bottom": 120,
        "mobile_padding_top": 80,
        "mobile_padding_bottom": 80,
        "margin_top": 0,
        "margin_top_mobile": 0,
        "background_color": "#f7f7f7"
      }
    }
  },
  "order": [
    "banner",
    "9fdc1847-6780-49ab-a505-596ad2d6b919",
    "fe97db31-543b-4849-b2be-8b75ad89be2a",
    "main",
    "bf576fbe-9cd2-4b50-a98e-488e9f2f41cf",
    "29cc8af8-f336-4fe8-98cc-84888081750f"
  ]
}
